setup.py
wryColorfulButtons/__init__.py
wryColorfulButtons.egg-info/PKG-INFO
wryColorfulButtons.egg-info/SOURCES.txt
wryColorfulButtons.egg-info/dependency_links.txt
wryColorfulButtons.egg-info/top_level.txt