Metadata-Version: 2.1
Name: wryColorfulButtons
Version: 0.0.1
Summary: ttkbootstrap彩色按钮/Ttkbootstrap color button
Home-page: http://wry.ljcsunrise.tech/wp
Author: Ruoyu Wang
Author-email: wry_beiyong12@outlook.com
License: MIT License
Platform: UNKNOWN
Requires: ttkbootstrap
